{"17": {"hight_level_topic": "Astronomy", "low_level_topic": "Galaxies"}, "18": {"hight_level_topic": "Mathematics", "low_level_topic": "Linear algebra"}, "28": {"hight_level_topic": "Physics", "low_level_topic": "Thermodynamics"}, "34": {"hight_level_topic": "Mathematics", "low_level_topic": "Statistics"}, "37": {"hight_level_topic": "Physics", "low_level_topic": "Nuclear Physics"}, "46": {"hight_level_topic": "Physics", "low_level_topic": "Geophysics"}, "78": {"hight_level_topic": "Mathematics", "low_level_topic": "Algebra"}, "98": {"hight_level_topic": "Mathematics", "low_level_topic": "Geometry and Topology"}, "105": {"hight_level_topic": "Chemistry", "low_level_topic": "Biochemistry"}, "137": {"hight_level_topic": "linguistics", "low_level_topic": "linguistics"}, "154": {"hight_level_topic": "Mathematics", "low_level_topic": "Algebraic geometry"}, "165": {"hight_level_topic": "Social Sciences", "low_level_topic": "Social Networks"}, "167": {"hight_level_topic": "Physics", "low_level_topic": "Particle physics"}, "168": {"hight_level_topic": "Physics", "low_level_topic": "Materials science"}, "181": {"hight_level_topic": "Mathematics", "low_level_topic": "Algebra"}, "192": {"hight_level_topic": "Mathematics", "low_level_topic": "Algebra"}, "195": {"hight_level_topic": "Evolutionary game theory", "low_level_topic": "Evolutionary game theory"}, "205": {"hight_level_topic": "Physics", "low_level_topic": "Nuclear Physics"}, "214": {"hight_level_topic": "Physics", "low_level_topic": "Crystallography"}, "253": {"hight_level_topic": "Medicine", "low_level_topic": "Cancer"}, "254": {"hight_level_topic": "linguistics", "low_level_topic": "creole languages"}, "260": {"hight_level_topic": "Economics", "low_level_topic": "Macroeconomics"}, "288": {"hight_level_topic": "Physics", "low_level_topic": "Relativity"}, "297": {"hight_level_topic": "Copyright Law", "low_level_topic": "Copyright Law"}, "310": {"hight_level_topic": "Computer Science", "low_level_topic": "Networking"}, "327": {"hight_level_topic": "Physics", "low_level_topic": "Condensed Matter Physics"}, "333": {"hight_level_topic": "Literature", "low_level_topic": "Novels"}, "347": {"hight_level_topic": "Astronomy", "low_level_topic": "Astronomy"}, "383": {"hight_level_topic": "Chemistry", "low_level_topic": "Inorganic Chemistry"}, "385": {"hight_level_topic": "Neuroscience", "low_level_topic": "Neurophysiology"}, "391": {"hight_level_topic": "Computer Science", "low_level_topic": "Artificial Intelligence"}, "439": {"hight_level_topic": "Mathematics", "low_level_topic": "Statistics"}, "463": {"hight_level_topic": "Physics", "low_level_topic": "Quantum Physics"}, "474": {"hight_level_topic": "Physics", "low_level_topic": "Meteorology"}, "509": {"hight_level_topic": "Taxonomy", "low_level_topic": "Taxonomy"}, "535": {"hight_level_topic": "Physics", "low_level_topic": "Electromagnetism"}, "538": {"hight_level_topic": "Science", "low_level_topic": "Engineering"}, "544": {"hight_level_topic": "Computer Science", "low_level_topic": "Data Structures and Algorithms"}, "562": {"hight_level_topic": "Physics", "low_level_topic": "Particle physics"}, "567": {"hight_level_topic": "Mathematics", "low_level_topic": "Algebraic Geometry"}, "584": {"hight_level_topic": "Mathematics", "low_level_topic": "Mathematical logic"}, "593": {"hight_level_topic": "Mathematics", "low_level_topic": "Analysis"}, "597": {"hight_level_topic": "Mathematics", "low_level_topic": "Algebra"}, "645": {"hight_level_topic": "Mathematics", "low_level_topic": "Algebraic geometry"}, "658": {"hight_level_topic": "Physics", "low_level_topic": "Optics"}, "671": {"hight_level_topic": "Wireless communication", "low_level_topic": "Wireless networks"}, "701": {"hight_level_topic": "Physics", "low_level_topic": "Gravitation"}, "736": {"hight_level_topic": "Mathematics", "low_level_topic": "Algorithms"}, "743": {"hight_level_topic": "Mathematics", "low_level_topic": "Control theory"}, "767": {"hight_level_topic": "Mathematics", "low_level_topic": "Graph theory"}, "776": {"hight_level_topic": "Mathematics", "low_level_topic": "Algebra"}, "778": {"hight_level_topic": "Physics", "low_level_topic": "Condensed Matter Physics"}, "788": {"hight_level_topic": "Mathematics", "low_level_topic": "Algebra"}, "810": {"hight_level_topic": "Chemistry", "low_level_topic": "Organic chemistry"}, "833": {"hight_level_topic": "Physics", "low_level_topic": "Mechanics"}, "834": {"hight_level_topic": "Mathematics", "low_level_topic": "Number theory"}, "838": {"hight_level_topic": "Mathematics", "low_level_topic": "Complex analysis"}, "852": {"hight_level_topic": "Mathematics", "low_level_topic": "Geometry"}, "855": {"hight_level_topic": "Physics", "low_level_topic": "Quantum Physics"}, "862": {"hight_level_topic": "Mathematics", "low_level_topic": "Statistics"}, "877": {"hight_level_topic": "Meteorology", "low_level_topic": "Atmospheric science"}, "908": {"hight_level_topic": "Mathematics", "low_level_topic": "Probability theory and stochastic processes"}, "926": {"hight_level_topic": "Cell biology", "low_level_topic": "Cell division"}, "973": {"hight_level_topic": "Mathematics", "low_level_topic": "Group theory"}, "974": {"hight_level_topic": "Astronomy", "low_level_topic": "Solar System"}, "1019": {"hight_level_topic": "Finance", "low_level_topic": "Stock market"}, "1028": {"hight_level_topic": "Mathematics", "low_level_topic": "Probability theory"}, "1029": {"hight_level_topic": "Acoustic emission", "low_level_topic": "Acoustic emission analysis"}, "1052": {"hight_level_topic": "Quantum Physics", "low_level_topic": "Quantum Computing"}, "1062": {"hight_level_topic": "Mathematics", "low_level_topic": "Combinatorics"}, "1089": {"hight_level_topic": "Physics", "low_level_topic": "Cosmology"}, "1127": {"hight_level_topic": "Real estate", "low_level_topic": "Las Vegas"}, "1148": {"hight_level_topic": "Mathematics", "low_level_topic": "Optimization"}, "1153": {"hight_level_topic": "Physics", "low_level_topic": "Optics"}, "1157": {"hight_level_topic": "Mathematics", "low_level_topic": "Geometry"}, "1163": {"hight_level_topic": "Physics", "low_level_topic": "Telegraphy"}, "1172": {"hight_level_topic": "Computer Science", "low_level_topic": "Computer Networks"}, "1198": {"hight_level_topic": "Computer Science", "low_level_topic": "Networking"}, "1226": {"hight_level_topic": "Physics", "low_level_topic": "Condensed Matter Physics"}, "1262": {"hight_level_topic": "Mathematics", "low_level_topic": "Number theory"}, "1276": {"hight_level_topic": "Biology", "low_level_topic": "Photosynthesis"}, "1284": {"hight_level_topic": "Mathematics", "low_level_topic": "Category theory"}, "1301": {"hight_level_topic": "Physics", "low_level_topic": "Magnetism"}, "1308": {"hight_level_topic": "Physics", "low_level_topic": "Optics"}, "1314": {"hight_level_topic": "Physics", "low_level_topic": "Neutrino Physics"}, "1325": {"hight_level_topic": "Mathematics", "low_level_topic": "Geometry"}, "1341": {"hight_level_topic": "Physics", "low_level_topic": "Optics"}, "1344": {"hight_level_topic": "Physics", "low_level_topic": "Astrophysics"}, "1372": {"hight_level_topic": "Chemistry", "low_level_topic": "Organic chemistry"}, "1401": {"hight_level_topic": "Food science", "low_level_topic": "Food contaminants"}, "1404": {"hight_level_topic": "Physics", "low_level_topic": "Statistical physics"}, "1432": {"hight_level_topic": "Physics", "low_level_topic": "Thermoacoustic and Photoacoustic Tomography"}, "1440": {"hight_level_topic": "Physics", "low_level_topic": "Theoretical physics"}, "1473": {"hight_level_topic": "Physics", "low_level_topic": "Condensed Matter Physics"}, "1516": {"hight_level_topic": "Physics", "low_level_topic": "Electromagnetism"}, "1546": {"hight_level_topic": "Physics", "low_level_topic": "Condensed Matter Physics"}, "1560": {"hight_level_topic": "Mathematics", "low_level_topic": "Algebra"}, "1566": {"hight_level_topic": "Physics", "low_level_topic": "Condensed Matter Physics"}, "1595": {"hight_level_topic": "Earth-Moon system", "low_level_topic": "Tectonics"}, "1610": {"hight_level_topic": "Mathematics", "low_level_topic": "Combinatorics"}, "1622": {"hight_level_topic": "Physics", "low_level_topic": "Condensed Matter Physics"}, "1640": {"hight_level_topic": "Mathematics", "low_level_topic": "Algebra"}, "1645": {"hight_level_topic": "Genetics", "low_level_topic": "Genetic code"}, "1650": {"hight_level_topic": "Mathematics", "low_level_topic": "Topology"}, "1666": {"hight_level_topic": "Science", "low_level_topic": "Research"}, "1669": {"hight_level_topic": "Mathematics", "low_level_topic": "Algebra"}, "1731": {"hight_level_topic": "Mathematics", "low_level_topic": "Geometry"}, "1733": {"hight_level_topic": "Mathematics", "low_level_topic": "Algebra"}, "1785": {"hight_level_topic": "Physics", "low_level_topic": "Semiconductor Physics"}, "1787": {"hight_level_topic": "Mathematics", "low_level_topic": "Graph theory"}, "1815": {"hight_level_topic": "Photovoltaics", "low_level_topic": "Photovoltaic cells"}, "1826": {"hight_level_topic": "Mathematics", "low_level_topic": "Calculus"}, "1867": {"hight_level_topic": "Mathematics", "low_level_topic": "Probability theory and stochastic processes"}, "1882": {"hight_level_topic": "Mathematics", "low_level_topic": "Applied Mathematics"}, "1885": {"hight_level_topic": "Physics", "low_level_topic": "Electromagnetism"}, "1891": {"hight_level_topic": "Mathematics", "low_level_topic": "Algebra"}, "1904": {"hight_level_topic": "Physics", "low_level_topic": "Quantum Physics"}, "1913": {"hight_level_topic": "Biology", "low_level_topic": "Mammals"}, "1916": {"hight_level_topic": "Computer Science", "low_level_topic": "Data Compression"}, "2004": {"hight_level_topic": "Physics", "low_level_topic": "Cellular Automata"}, "2065": {"hight_level_topic": "Physics", "low_level_topic": "Electromagnetism"}, "2077": {"hight_level_topic": "Physics", "low_level_topic": "Relativity"}, "2090": {"hight_level_topic": "Mathematics", "low_level_topic": "Functional Analysis"}, "2120": {"hight_level_topic": "Physics", "low_level_topic": "Particle physics"}, "2123": {"hight_level_topic": "Mathematics", "low_level_topic": "Geometry"}, "2135": {"hight_level_topic": "Computer Science", "low_level_topic": "Artificial Intelligence"}, "2152": {"hight_level_topic": "Mathematics", "low_level_topic": "Probability theory and stochastic processes"}, "2155": {"hight_level_topic": "Chemistry", "low_level_topic": "Physical Chemistry"}, "2215": {"hight_level_topic": "Mathematics", "low_level_topic": "Topology"}, "2224": {"hight_level_topic": "Physics", "low_level_topic": "Quantum Physics"}, "2257": {"hight_level_topic": "Mathematics", "low_level_topic": "Geometry"}, "2258": {"hight_level_topic": "Physics", "low_level_topic": "Gravitation"}, "2278": {"hight_level_topic": "Geology", "low_level_topic": "Geology"}, "2301": {"hight_level_topic": "Computer Science", "low_level_topic": "Computer Architecture"}, "2305": {"hight_level_topic": "Physics", "low_level_topic": "Condensed Matter Physics"}, "2339": {"hight_level_topic": "Mathematics", "low_level_topic": "Topology"}, "2368": {"hight_level_topic": "Physics", "low_level_topic": "Magnetism"}, "2373": {"hight_level_topic": "Mathematics", "low_level_topic": "Group theory"}}